{
  "years": [
    2003,
    2007,
    2009,
    2013,
    2016,
    2017,
    2021,
    2024
  ],
  "constituencies": [
    "Norðvesturkjördæmi",
    "Norðausturkjördæmi",
    "Suðurkjördæmi",
    "Suðvesturkjördæmi",
    "Reykjavíkurkjördæmi suður",
    "Reykjavíkurkjördæmi norður"
  ],
  "results": [
    {
      "year": 2003,
      "constituency": "Norðvesturkjördæmi",
      "party": "Sjálfstæðisflokkur",
      "percent": 29.6
    },
    {
      "year": 2003,
      "constituency": "Norðvesturkjördæmi",
      "party": "Samfylkingin",
      "percent": 23.2
    },
    {
      "year": 2003,
      "constituency": "Norðvesturkjördæmi",
      "party": "Framsóknarflokkur",
      "percent": 21.7
    },
    {
      "year": 2003,
      "constituency": "Norðvesturkjördæmi",
      "party": "Frjálslyndi flokkurinn",
      "percent": 14.2
    },
    {
      "year": 2003,
      "constituency": "Norðvesturkjördæmi",
      "party": "Vinstrihreyfingin - grænt framboð",
      "percent": 10.6
    },
    {
      "year": 2003,
      "constituency": "Norðvesturkjördæmi",
      "party": "Nýtt afl",
      "percent": 0.7
    },
    {
      "year": 2003,
      "constituency": "Norðausturkjördæmi",
      "party": "Framsóknarflokkur",
      "percent": 32.8
    },
    {
      "year": 2003,
      "constituency": "Norðausturkjördæmi",
      "party": "Sjálfstæðisflokkur",
      "percent": 23.5
    },
    {
      "year": 2003,
      "constituency": "Norðausturkjördæmi",
      "party": "Samfylkingin",
      "percent": 23.4
    },
    {
      "year": 2003,
      "constituency": "Norðausturkjördæmi",
      "party": "Vinstrihreyfingin - grænt framboð",
      "percent": 14.1
    },
    {
      "year": 2003,
      "constituency": "Norðausturkjördæmi",
      "party": "Frjálslyndi flokkurinn",
      "percent": 5.6
    },
    {
      "year": 2003,
      "constituency": "Norðausturkjördæmi",
      "party": "Nýtt afl",
      "percent": 0.6
    },
    {
      "year": 2003,
      "constituency": "Suðurkjördæmi",
      "party": "Samfylkingin",
      "percent": 29.7
    },
    {
      "year": 2003,
      "constituency": "Suðurkjördæmi",
      "party": "Sjálfstæðisflokkur",
      "percent": 29.2
    },
    {
      "year": 2003,
      "constituency": "Suðurkjördæmi",
      "party": "Framsóknarflokkur",
      "percent": 23.7
    },
    {
      "year": 2003,
      "constituency": "Suðurkjördæmi",
      "party": "Frjálslyndi flokkurinn",
      "percent": 8.7
    },
    {
      "year": 2003,
      "constituency": "Suðurkjördæmi",
      "party": "Vinstrihreyfingin - grænt framboð",
      "percent": 4.7
    },
    {
      "year": 2003,
      "constituency": "Suðurkjördæmi",
      "party": "Framboð óháðra í suðurkjördæmi",
      "percent": 3.4
    },
    {
      "year": 2003,
      "constituency": "Suðurkjördæmi",
      "party": "Nýtt afl",
      "percent": 0.7
    },
    {
      "year": 2003,
      "constituency": "Suðvesturkjördæmi",
      "party": "Sjálfstæðisflokkur",
      "percent": 38.4
    },
    {
      "year": 2003,
      "constituency": "Suðvesturkjördæmi",
      "party": "Samfylkingin",
      "percent": 32.8
    },
    {
      "year": 2003,
      "constituency": "Suðvesturkjördæmi",
      "party": "Framsóknarflokkur",
      "percent": 14.9
    },
    {
      "year": 2003,
      "constituency": "Suðvesturkjördæmi",
      "party": "Frjálslyndi flokkurinn",
      "percent": 6.7
    },
    {
      "year": 2003,
      "constituency": "Suðvesturkjördæmi",
      "party": "Vinstrihreyfingin - grænt framboð",
      "percent": 6.2
    },
    {
      "year": 2003,
      "constituency": "Suðvesturkjördæmi",
      "party": "Nýtt afl",
      "percent": 0.9
    },
    {
      "year": 2003,
      "constituency": "Reykjavíkurkjördæmi suður",
      "party": "Sjálfstæðisflokkur",
      "percent": 38
    },
    {
      "year": 2003,
      "constituency": "Reykjavíkurkjördæmi suður",
      "party": "Samfylkingin",
      "percent": 33.3
    },
    {
      "year": 2003,
      "constituency": "Reykjavíkurkjördæmi suður",
      "party": "Framsóknarflokkur",
      "percent": 11.3
    },
    {
      "year": 2003,
      "constituency": "Reykjavíkurkjördæmi suður",
      "party": "Vinstrihreyfingin - grænt framboð",
      "percent": 9.3
    },
    {
      "year": 2003,
      "constituency": "Reykjavíkurkjördæmi suður",
      "party": "Frjálslyndi flokkurinn",
      "percent": 6.6
    },
    {
      "year": 2003,
      "constituency": "Reykjavíkurkjördæmi suður",
      "party": "Nýtt afl",
      "percent": 1.4
    },
    {
      "year": 2003,
      "constituency": "Reykjavíkurkjördæmi norður",
      "party": "Samfylkingin",
      "percent": 36.3
    },
    {
      "year": 2003,
      "constituency": "Reykjavíkurkjördæmi norður",
      "party": "Sjálfstæðisflokkur",
      "percent": 35.5
    },
    {
      "year": 2003,
      "constituency": "Reykjavíkurkjördæmi norður",
      "party": "Framsóknarflokkur",
      "percent": 11.6
    },
    {
      "year": 2003,
      "constituency": "Reykjavíkurkjördæmi norður",
      "party": "Vinstrihreyfingin - grænt framboð",
      "percent": 9.8
    },
    {
      "year": 2003,
      "constituency": "Reykjavíkurkjördæmi norður",
      "party": "Frjálslyndi flokkurinn",
      "percent": 5.5
    },
    {
      "year": 2003,
      "constituency": "Reykjavíkurkjördæmi norður",
      "party": "Nýtt afl",
      "percent": 1.3
    },
    {
      "year": 2007,
      "constituency": "Norðvesturkjördæmi",
      "party": "Sjálfstæðisflokkur",
      "percent": 29.1
    },
    {
      "year": 2007,
      "constituency": "Norðvesturkjördæmi",
      "party": "Samfylkingin",
      "percent": 21.2
    },
    {
      "year": 2007,
      "constituency": "Norðvesturkjördæmi",
      "party": "Framsóknarflokkur",
      "percent": 18.8
    },
    {
      "year": 2007,
      "constituency": "Norðvesturkjördæmi",
      "party": "Vinstrihreyfingin - grænt framboð",
      "percent": 16
    },
    {
      "year": 2007,
      "constituency": "Norðvesturkjördæmi",
      "party": "Frjálslyndi flokkurinn",
      "percent": 13.6
    },
    {
      "year": 2007,
      "constituency": "Norðvesturkjördæmi",
      "party": "Íslandshreyfingin",
      "percent": 1.4
    },
    {
      "year": 2007,
      "constituency": "Norðausturkjördæmi",
      "party": "Sjálfstæðisflokkur",
      "percent": 28
    },
    {
      "year": 2007,
      "constituency": "Norðausturkjördæmi",
      "party": "Framsóknarflokkur",
      "percent": 24.6
    },
    {
      "year": 2007,
      "constituency": "Norðausturkjördæmi",
      "party": "Samfylkingin",
      "percent": 20.8
    },
    {
      "year": 2007,
      "constituency": "Norðausturkjördæmi",
      "party": "Vinstrihreyfingin - grænt framboð",
      "percent": 19.6
    },
    {
      "year": 2007,
      "constituency": "Norðausturkjördæmi",
      "party": "Frjálslyndi flokkurinn",
      "percent": 5.9
    },
    {
      "year": 2007,
      "constituency": "Norðausturkjördæmi",
      "party": "Íslandshreyfingin",
      "percent": 1.2
    },
    {
      "year": 2007,
      "constituency": "Suðurkjördæmi",
      "party": "Sjálfstæðisflokkur",
      "percent": 36
    },
    {
      "year": 2007,
      "constituency": "Suðurkjördæmi",
      "party": "Samfylkingin",
      "percent": 26.8
    },
    {
      "year": 2007,
      "constituency": "Suðurkjördæmi",
      "party": "Framsóknarflokkur",
      "percent": 18.7
    },
    {
      "year": 2007,
      "constituency": "Suðurkjördæmi",
      "party": "Vinstrihreyfingin - grænt framboð",
      "percent": 9.9
    },
    {
      "year": 2007,
      "constituency": "Suðurkjördæmi",
      "party": "Frjálslyndi flokkurinn",
      "percent": 7
    },
    {
      "year": 2007,
      "constituency": "Suðurkjördæmi",
      "party": "Íslandshreyfingin",
      "percent": 1.7
    },
    {
      "year": 2007,
      "constituency": "Suðvesturkjördæmi",
      "party": "Sjálfstæðisflokkur",
      "percent": 42.6
    },
    {
      "year": 2007,
      "constituency": "Suðvesturkjördæmi",
      "party": "Samfylkingin",
      "percent": 28.4
    },
    {
      "year": 2007,
      "constituency": "Suðvesturkjördæmi",
      "party": "Vinstrihreyfingin - grænt framboð",
      "percent": 11.6
    },
    {
      "year": 2007,
      "constituency": "Suðvesturkjördæmi",
      "party": "Framsóknarflokkur",
      "percent": 7.2
    },
    {
      "year": 2007,
      "constituency": "Suðvesturkjördæmi",
      "party": "Frjálslyndi flokkurinn",
      "percent": 6.7
    },
    {
      "year": 2007,
      "constituency": "Suðvesturkjördæmi",
      "party": "Íslandshreyfingin",
      "percent": 3.5
    },
    {
      "year": 2007,
      "constituency": "Reykjavíkurkjördæmi suður",
      "party": "Sjálfstæðisflokkur",
      "percent": 39.2
    },
    {
      "year": 2007,
      "constituency": "Reykjavíkurkjördæmi suður",
      "party": "Samfylkingin",
      "percent": 29
    },
    {
      "year": 2007,
      "constituency": "Reykjavíkurkjördæmi suður",
      "party": "Vinstrihreyfingin - grænt framboð",
      "percent": 14.4
    },
    {
      "year": 2007,
      "constituency": "Reykjavíkurkjördæmi suður",
      "party": "Frjálslyndi flokkurinn",
      "percent": 6.8
    },
    {
      "year": 2007,
      "constituency": "Reykjavíkurkjördæmi suður",
      "party": "Framsóknarflokkur",
      "percent": 5.9
    },
    {
      "year": 2007,
      "constituency": "Reykjavíkurkjördæmi suður",
      "party": "Íslandshreyfingin",
      "percent": 4.8
    },
    {
      "year": 2007,
      "constituency": "Reykjavíkurkjördæmi norður",
      "party": "Sjálfstæðisflokkur",
      "percent": 36.4
    },
    {
      "year": 2007,
      "constituency": "Reykjavíkurkjördæmi norður",
      "party": "Samfylkingin",
      "percent": 29.2
    },
    {
      "year": 2007,
      "constituency": "Reykjavíkurkjördæmi norður",
      "party": "Vinstrihreyfingin - grænt framboð",
      "percent": 16.9
    },
    {
      "year": 2007,
      "constituency": "Reykjavíkurkjördæmi norður",
      "party": "Frjálslyndi flokkurinn",
      "percent": 6.3
    },
    {
      "year": 2007,
      "constituency": "Reykjavíkurkjördæmi norður",
      "party": "Framsóknarflokkur",
      "percent": 6.2
    },
    {
      "year": 2007,
      "constituency": "Reykjavíkurkjördæmi norður",
      "party": "Íslandshreyfingin",
      "percent": 4.9
    },
    {
      "year": 2009,
      "constituency": "Norðvesturkjördæmi",
      "party": "Sjálfstæðisflokkur",
      "percent": 22.9
    },
    {
      "year": 2009,
      "constituency": "Norðvesturkjördæmi",
      "party": "Vinstrihreyfingin - grænt framboð",
      "percent": 22.8
    },
    {
      "year": 2009,
      "constituency": "Norðvesturkjördæmi",
      "party": "Samfylkingin",
      "percent": 22.7
    },
    {
      "year": 2009,
      "constituency": "Norðvesturkjördæmi",
      "party": "Framsóknarflokkur",
      "percent": 22.5
    },
    {
      "year": 2009,
      "constituency": "Norðvesturkjördæmi",
      "party": "Frjálslyndi flokkurinn",
      "percent": 5.3
    },
    {
      "year": 2009,
      "constituency": "Norðvesturkjördæmi",
      "party": "Borgarahreyfingin",
      "percent": 3.3
    },
    {
      "year": 2009,
      "constituency": "Norðvesturkjördæmi",
      "party": "Lýðræðishreyfingin",
      "percent": 0.4
    },
    {
      "year": 2009,
      "constituency": "Norðausturkjördæmi",
      "party": "Vinstrihreyfingin - grænt framboð",
      "percent": 29.7
    },
    {
      "year": 2009,
      "constituency": "Norðausturkjördæmi",
      "party": "Framsóknarflokkur",
      "percent": 25.3
    },
    {
      "year": 2009,
      "constituency": "Norðausturkjördæmi",
      "party": "Samfylkingin",
      "percent": 22.7
    },
    {
      "year": 2009,
      "constituency": "Norðausturkjördæmi",
      "party": "Sjálfstæðisflokkur",
      "percent": 17.5
    },
    {
      "year": 2009,
      "constituency": "Norðausturkjördæmi",
      "party": "Borgarahreyfingin",
      "percent": 3
    },
    {
      "year": 2009,
      "constituency": "Norðausturkjördæmi",
      "party": "Frjálslyndi flokkurinn",
      "percent": 1.6
    },
    {
      "year": 2009,
      "constituency": "Norðausturkjördæmi",
      "party": "Lýðræðishreyfingin",
      "percent": 0.3
    },
    {
      "year": 2009,
      "constituency": "Suðurkjördæmi",
      "party": "Samfylkingin",
      "percent": 28
    },
    {
      "year": 2009,
      "constituency": "Suðurkjördæmi",
      "party": "Sjálfstæðisflokkur",
      "percent": 26.2
    },
    {
      "year": 2009,
      "constituency": "Suðurkjördæmi",
      "party": "Framsóknarflokkur",
      "percent": 20
    },
    {
      "year": 2009,
      "constituency": "Suðurkjördæmi",
      "party": "Vinstrihreyfingin - grænt framboð",
      "percent": 17.1
    },
    {
      "year": 2009,
      "constituency": "Suðurkjördæmi",
      "party": "Borgarahreyfingin",
      "percent": 5.1
    },
    {
      "year": 2009,
      "constituency": "Suðurkjördæmi",
      "party": "Frjálslyndi flokkurinn",
      "percent": 3.1
    },
    {
      "year": 2009,
      "constituency": "Suðurkjördæmi",
      "party": "Lýðræðishreyfingin",
      "percent": 0.5
    },
    {
      "year": 2009,
      "constituency": "Suðvesturkjördæmi",
      "party": "Samfylkingin",
      "percent": 32.2
    },
    {
      "year": 2009,
      "constituency": "Suðvesturkjördæmi",
      "party": "Sjálfstæðisflokkur",
      "percent": 27.6
    },
    {
      "year": 2009,
      "constituency": "Suðvesturkjördæmi",
      "party": "Vinstrihreyfingin - grænt framboð",
      "percent": 17.4
    },
    {
      "year": 2009,
      "constituency": "Suðvesturkjördæmi",
      "party": "Framsóknarflokkur",
      "percent": 11.6
    },
    {
      "year": 2009,
      "constituency": "Suðvesturkjördæmi",
      "party": "Borgarahreyfingin",
      "percent": 9.1
    },
    {
      "year": 2009,
      "constituency": "Suðvesturkjördæmi",
      "party": "Frjálslyndi flokkurinn",
      "percent": 1.5
    },
    {
      "year": 2009,
      "constituency": "Suðvesturkjördæmi",
      "party": "Lýðræðishreyfingin",
      "percent": 0.6
    },
    {
      "year": 2009,
      "constituency": "Reykjavíkurkjördæmi suður",
      "party": "Samfylkingin",
      "percent": 32.9
    },
    {
      "year": 2009,
      "constituency": "Reykjavíkurkjördæmi suður",
      "party": "Sjálfstæðisflokkur",
      "percent": 23.2
    },
    {
      "year": 2009,
      "constituency": "Reykjavíkurkjördæmi suður",
      "party": "Vinstrihreyfingin - grænt framboð",
      "percent": 22.9
    },
    {
      "year": 2009,
      "constituency": "Reykjavíkurkjördæmi suður",
      "party": "Framsóknarflokkur",
      "percent": 9.7
    },
    {
      "year": 2009,
      "constituency": "Reykjavíkurkjördæmi suður",
      "party": "Borgarahreyfingin",
      "percent": 8.7
    },
    {
      "year": 2009,
      "constituency": "Reykjavíkurkjördæmi suður",
      "party": "Frjálslyndi flokkurinn",
      "percent": 2
    },
    {
      "year": 2009,
      "constituency": "Reykjavíkurkjördæmi suður",
      "party": "Lýðræðishreyfingin",
      "percent": 0.6
    },
    {
      "year": 2009,
      "constituency": "Reykjavíkurkjördæmi norður",
      "party": "Samfylkingin",
      "percent": 32.9
    },
    {
      "year": 2009,
      "constituency": "Reykjavíkurkjördæmi norður",
      "party": "Vinstrihreyfingin - grænt framboð",
      "percent": 24
    },
    {
      "year": 2009,
      "constituency": "Reykjavíkurkjördæmi norður",
      "party": "Sjálfstæðisflokkur",
      "percent": 21.4
    },
    {
      "year": 2009,
      "constituency": "Reykjavíkurkjördæmi norður",
      "party": "Framsóknarflokkur",
      "percent": 9.6
    },
    {
      "year": 2009,
      "constituency": "Reykjavíkurkjördæmi norður",
      "party": "Borgarahreyfingin",
      "percent": 9.6
    },
    {
      "year": 2009,
      "constituency": "Reykjavíkurkjördæmi norður",
      "party": "Frjálslyndi flokkurinn",
      "percent": 1.6
    },
    {
      "year": 2009,
      "constituency": "Reykjavíkurkjördæmi norður",
      "party": "Lýðræðishreyfingin",
      "percent": 0.9
    },
    {
      "year": 2013,
      "constituency": "Norðvesturkjördæmi",
      "party": "Framsóknarflokkur",
      "percent": 35.2
    },
    {
      "year": 2013,
      "constituency": "Norðvesturkjördæmi",
      "party": "Sjálfstæðisflokkur",
      "percent": 24.7
    },
    {
      "year": 2013,
      "constituency": "Norðvesturkjördæmi",
      "party": "Samfylkingin",
      "percent": 12.2
    },
    {
      "year": 2013,
      "constituency": "Norðvesturkjördæmi",
      "party": "Vinstrihreyfingin - grænt framboð",
      "percent": 8.5
    },
    {
      "year": 2013,
      "constituency": "Norðvesturkjördæmi",
      "party": "Björt framtíð",
      "percent": 4.6
    },
    {
      "year": 2013,
      "constituency": "Norðvesturkjördæmi",
      "party": "Regnboginn",
      "percent": 4.5
    },
    {
      "year": 2013,
      "constituency": "Norðvesturkjördæmi",
      "party": "Píratar",
      "percent": 3.1
    },
    {
      "year": 2013,
      "constituency": "Norðvesturkjördæmi",
      "party": "Landsbyggðarflokkurinn",
      "percent": 1.9
    },
    {
      "year": 2013,
      "constituency": "Norðvesturkjördæmi",
      "party": "Dögun",
      "percent": 1.9
    },
    {
      "year": 2013,
      "constituency": "Norðausturkjördæmi",
      "party": "Framsóknarflokkur",
      "percent": 34.6
    },
    {
      "year": 2013,
      "constituency": "Norðausturkjördæmi",
      "party": "Sjálfstæðisflokkur",
      "percent": 22.6
    },
    {
      "year": 2013,
      "constituency": "Norðausturkjördæmi",
      "party": "Vinstrihreyfingin - grænt framboð",
      "percent": 15.8
    },
    {
      "year": 2013,
      "constituency": "Norðausturkjördæmi",
      "party": "Samfylkingin",
      "percent": 10.6
    },
    {
      "year": 2013,
      "constituency": "Norðausturkjördæmi",
      "party": "Björt framtíð",
      "percent": 6.5
    },
    {
      "year": 2013,
      "constituency": "Norðausturkjördæmi",
      "party": "Píratar",
      "percent": 3
    },
    {
      "year": 2013,
      "constituency": "Norðausturkjördæmi",
      "party": "Dögun",
      "percent": 1.9
    },
    {
      "year": 2013,
      "constituency": "Norðausturkjördæmi",
      "party": "Hægri grænir",
      "percent": 1.3
    },
    {
      "year": 2013,
      "constituency": "Norðausturkjördæmi",
      "party": "Regnboginn",
      "percent": 1.3
    },
    {
      "year": 2013,
      "constituency": "Suðurkjördæmi",
      "party": "Framsóknarflokkur",
      "percent": 34.5
    },
    {
      "year": 2013,
      "constituency": "Suðurkjördæmi",
      "party": "Sjálfstæðisflokkur",
      "percent": 28.3
    },
    {
      "year": 2013,
      "constituency": "Suðurkjördæmi",
      "party": "Samfylkingin",
      "percent": 10.2
    },
    {
      "year": 2013,
      "constituency": "Suðurkjördæmi",
      "party": "Vinstrihreyfingin - grænt framboð",
      "percent": 5.9
    },
    {
      "year": 2013,
      "constituency": "Suðurkjördæmi",
      "party": "Píratar",
      "percent": 4.7
    },
    {
      "year": 2013,
      "constituency": "Suðurkjördæmi",
      "party": "Björt framtíð",
      "percent": 4.5
    },
    {
      "year": 2013,
      "constituency": "Suðurkjördæmi",
      "party": "Dögun",
      "percent": 3.4
    },
    {
      "year": 2013,
      "constituency": "Suðurkjördæmi",
      "party": "Flokkur heimilanna",
      "percent": 2.9
    },
    {
      "year": 2013,
      "constituency": "Suðurkjördæmi",
      "party": "Hægri grænir",
      "percent": 2.6
    },
    {
      "year": 2013,
      "constituency": "Suðvesturkjördæmi",
      "party": "Sjálfstæðisflokkur",
      "percent": 30.7
    },
    {
      "year": 2013,
      "constituency": "Suðvesturkjördæmi",
      "party": "Framsóknarflokkur",
      "percent": 21.5
    },
    {
      "year": 2013,
      "constituency": "Suðvesturkjördæmi",
      "party": "Samfylkingin",
      "percent": 13.6
    },
    {
      "year": 2013,
      "constituency": "Suðvesturkjördæmi",
      "party": "Björt framtíð",
      "percent": 9.2
    },
    {
      "year": 2013,
      "constituency": "Suðvesturkjördæmi",
      "party": "Vinstrihreyfingin - grænt framboð",
      "percent": 7.9
    },
    {
      "year": 2013,
      "constituency": "Suðvesturkjördæmi",
      "party": "Píratar",
      "percent": 5
    },
    {
      "year": 2013,
      "constituency": "Suðvesturkjördæmi",
      "party": "Dögun",
      "percent": 3.8
    },
    {
      "year": 2013,
      "constituency": "Suðvesturkjördæmi",
      "party": "Flokkur heimilanna",
      "percent": 3.6
    },
    {
      "year": 2013,
      "constituency": "Suðvesturkjördæmi",
      "party": "Lýðræðisvaktin",
      "percent": 2.4
    },
    {
      "year": 2013,
      "constituency": "Reykjavíkurkjördæmi suður",
      "party": "Sjálfstæðisflokkur",
      "percent": 26.8
    },
    {
      "year": 2013,
      "constituency": "Reykjavíkurkjördæmi suður",
      "party": "Framsóknarflokkur",
      "percent": 16.8
    },
    {
      "year": 2013,
      "constituency": "Reykjavíkurkjördæmi suður",
      "party": "Samfylkingin",
      "percent": 14.2
    },
    {
      "year": 2013,
      "constituency": "Reykjavíkurkjördæmi suður",
      "party": "Vinstrihreyfingin - grænt framboð",
      "percent": 12.1
    },
    {
      "year": 2013,
      "constituency": "Reykjavíkurkjördæmi suður",
      "party": "Björt framtíð",
      "percent": 10.7
    },
    {
      "year": 2013,
      "constituency": "Reykjavíkurkjördæmi suður",
      "party": "Píratar",
      "percent": 6.2
    },
    {
      "year": 2013,
      "constituency": "Reykjavíkurkjördæmi suður",
      "party": "Flokkur heimilanna",
      "percent": 3.9
    },
    {
      "year": 2013,
      "constituency": "Reykjavíkurkjördæmi suður",
      "party": "Dögun",
      "percent": 3.3
    },
    {
      "year": 2013,
      "constituency": "Reykjavíkurkjördæmi suður",
      "party": "Lýðræðisvaktin",
      "percent": 2.9
    },
    {
      "year": 2013,
      "constituency": "Reykjavíkurkjördæmi norður",
      "party": "Sjálfstæðisflokkur",
      "percent": 23.4
    },
    {
      "year": 2013,
      "constituency": "Reykjavíkurkjördæmi norður",
      "party": "Framsóknarflokkur",
      "percent": 16.4
    },
    {
      "year": 2013,
      "constituency": "Reykjavíkurkjördæmi norður",
      "party": "Vinstrihreyfingin - grænt framboð",
      "percent": 15.7
    },
    {
      "year": 2013,
      "constituency": "Reykjavíkurkjördæmi norður",
      "party": "Samfylkingin",
      "percent": 14.3
    },
    {
      "year": 2013,
      "constituency": "Reykjavíkurkjördæmi norður",
      "party": "Björt framtíð",
      "percent": 10.2
    },
    {
      "year": 2013,
      "constituency": "Reykjavíkurkjördæmi norður",
      "party": "Píratar",
      "percent": 6.9
    },
    {
      "year": 2013,
      "constituency": "Reykjavíkurkjördæmi norður",
      "party": "Lýðræðisvaktin",
      "percent": 4
    },
    {
      "year": 2013,
      "constituency": "Reykjavíkurkjördæmi norður",
      "party": "Flokkur heimilanna",
      "percent": 3.7
    },
    {
      "year": 2013,
      "constituency": "Reykjavíkurkjördæmi norður",
      "party": "Dögun",
      "percent": 3.1
    },
    {
      "year": 2016,
      "constituency": "Norðvesturkjördæmi",
      "party": "Sjálfstæðisflokkur",
      "percent": 29.5
    },
    {
      "year": 2016,
      "constituency": "Norðvesturkjördæmi",
      "party": "Framsóknarflokkur",
      "percent": 20.8
    },
    {
      "year": 2016,
      "constituency": "Norðvesturkjördæmi",
      "party": "Vinstrihreyfingin - grænt framboð",
      "percent": 18.1
    },
    {
      "year": 2016,
      "constituency": "Norðvesturkjördæmi",
      "party": "Píratar",
      "percent": 10.9
    },
    {
      "year": 2016,
      "constituency": "Norðvesturkjördæmi",
      "party": "Samfylkingin",
      "percent": 6.3
    },
    {
      "year": 2016,
      "constituency": "Norðvesturkjördæmi",
      "party": "Viðreisn",
      "percent": 6.2
    },
    {
      "year": 2016,
      "constituency": "Norðvesturkjördæmi",
      "party": "Björt framtíð",
      "percent": 3.5
    },
    {
      "year": 2016,
      "constituency": "Norðvesturkjördæmi",
      "party": "Flokkur fólksins",
      "percent": 2.5
    },
    {
      "year": 2016,
      "constituency": "Norðvesturkjördæmi",
      "party": "Dögun",
      "percent": 1.7
    },
    {
      "year": 2016,
      "constituency": "Norðausturkjördæmi",
      "party": "Sjálfstæðisflokkur",
      "percent": 26.5
    },
    {
      "year": 2016,
      "constituency": "Norðausturkjördæmi",
      "party": "Framsóknarflokkur",
      "percent": 20
    },
    {
      "year": 2016,
      "constituency": "Norðausturkjördæmi",
      "party": "Vinstrihreyfingin - grænt framboð",
      "percent": 20
    },
    {
      "year": 2016,
      "constituency": "Norðausturkjördæmi",
      "party": "Píratar",
      "percent": 10
    },
    {
      "year": 2016,
      "constituency": "Norðausturkjördæmi",
      "party": "Samfylkingin",
      "percent": 8
    },
    {
      "year": 2016,
      "constituency": "Norðausturkjördæmi",
      "party": "Viðreisn",
      "percent": 6.5
    },
    {
      "year": 2016,
      "constituency": "Norðausturkjördæmi",
      "party": "Björt framtíð",
      "percent": 3.4
    },
    {
      "year": 2016,
      "constituency": "Norðausturkjördæmi",
      "party": "Flokkur fólksins",
      "percent": 2.8
    },
    {
      "year": 2016,
      "constituency": "Norðausturkjördæmi",
      "party": "Dögun",
      "percent": 1.8
    },
    {
      "year": 2016,
      "constituency": "Suðurkjördæmi",
      "party": "Sjálfstæðisflokkur",
      "percent": 31.5
    },
    {
      "year": 2016,
      "constituency": "Suðurkjördæmi",
      "party": "Framsóknarflokkur",
      "percent": 19.1
    },
    {
      "year": 2016,
      "constituency": "Suðurkjördæmi",
      "party": "Píratar",
      "percent": 12.8
    },
    {
      "year": 2016,
      "constituency": "Suðurkjördæmi",
      "party": "Vinstrihreyfingin - grænt framboð",
      "percent": 10.2
    },
    {
      "year": 2016,
      "constituency": "Suðurkjördæmi",
      "party": "Viðreisn",
      "percent": 7.3
    },
    {
      "year": 2016,
      "constituency": "Suðurkjördæmi",
      "party": "Samfylkingin",
      "percent": 6.4
    },
    {
      "year": 2016,
      "constituency": "Suðurkjördæmi",
      "party": "Björt framtíð",
      "percent": 5.8
    },
    {
      "year": 2016,
      "constituency": "Suðurkjördæmi",
      "party": "Flokkur fólksins",
      "percent": 3.6
    },
    {
      "year": 2016,
      "constituency": "Suðurkjördæmi",
      "party": "Dögun",
      "percent": 2.3
    },
    {
      "year": 2016,
      "constituency": "Suðvesturkjördæmi",
      "party": "Sjálfstæðisflokkur",
      "percent": 33.9
    },
    {
      "year": 2016,
      "constituency": "Suðvesturkjördæmi",
      "party": "Píratar",
      "percent": 13.6
    },
    {
      "year": 2016,
      "constituency": "Suðvesturkjördæmi",
      "party": "Viðreisn",
      "percent": 12.9
    },
    {
      "year": 2016,
      "constituency": "Suðvesturkjördæmi",
      "party": "Vinstrihreyfingin - grænt framboð",
      "percent": 12
    },
    {
      "year": 2016,
      "constituency": "Suðvesturkjördæmi",
      "party": "Björt framtíð",
      "percent": 10.2
    },
    {
      "year": 2016,
      "constituency": "Suðvesturkjördæmi",
      "party": "Framsóknarflokkur",
      "percent": 7.6
    },
    {
      "year": 2016,
      "constituency": "Suðvesturkjördæmi",
      "party": "Samfylkingin",
      "percent": 4.8
    },
    {
      "year": 2016,
      "constituency": "Suðvesturkjördæmi",
      "party": "Flokkur fólksins",
      "percent": 3.3
    },
    {
      "year": 2016,
      "constituency": "Suðvesturkjördæmi",
      "party": "Dögun",
      "percent": 1.7
    },
    {
      "year": 2016,
      "constituency": "Reykjavíkurkjördæmi suður",
      "party": "Sjálfstæðisflokkur",
      "percent": 25.6
    },
    {
      "year": 2016,
      "constituency": "Reykjavíkurkjördæmi suður",
      "party": "Vinstrihreyfingin - grænt framboð",
      "percent": 17.6
    },
    {
      "year": 2016,
      "constituency": "Reykjavíkurkjördæmi suður",
      "party": "Píratar",
      "percent": 17.3
    },
    {
      "year": 2016,
      "constituency": "Reykjavíkurkjördæmi suður",
      "party": "Viðreisn",
      "percent": 12.7
    },
    {
      "year": 2016,
      "constituency": "Reykjavíkurkjördæmi suður",
      "party": "Framsóknarflokkur",
      "percent": 7.4
    },
    {
      "year": 2016,
      "constituency": "Reykjavíkurkjördæmi suður",
      "party": "Björt framtíð",
      "percent": 7.2
    },
    {
      "year": 2016,
      "constituency": "Reykjavíkurkjördæmi suður",
      "party": "Samfylkingin",
      "percent": 5.6
    },
    {
      "year": 2016,
      "constituency": "Reykjavíkurkjördæmi suður",
      "party": "Flokkur fólksins",
      "percent": 4.6
    },
    {
      "year": 2016,
      "constituency": "Reykjavíkurkjördæmi suður",
      "party": "Dögun",
      "percent": 1.7
    },
    {
      "year": 2016,
      "constituency": "Reykjavíkurkjördæmi norður",
      "party": "Sjálfstæðisflokkur",
      "percent": 24.4
    },
    {
      "year": 2016,
      "constituency": "Reykjavíkurkjördæmi norður",
      "party": "Vinstrihreyfingin - grænt framboð",
      "percent": 20.9
    },
    {
      "year": 2016,
      "constituency": "Reykjavíkurkjördæmi norður",
      "party": "Píratar",
      "percent": 19
    },
    {
      "year": 2016,
      "constituency": "Reykjavíkurkjördæmi norður",
      "party": "Viðreisn",
      "percent": 11.6
    },
    {
      "year": 2016,
      "constituency": "Reykjavíkurkjördæmi norður",
      "party": "Björt framtíð",
      "percent": 7.6
    },
    {
      "year": 2016,
      "constituency": "Reykjavíkurkjördæmi norður",
      "party": "Framsóknarflokkur",
      "percent": 5.7
    },
    {
      "year": 2016,
      "constituency": "Reykjavíkurkjördæmi norður",
      "party": "Samfylkingin",
      "percent": 5.2
    },
    {
      "year": 2016,
      "constituency": "Reykjavíkurkjördæmi norður",
      "party": "Flokkur fólksins",
      "percent": 3.8
    },
    {
      "year": 2016,
      "constituency": "Reykjavíkurkjördæmi norður",
      "party": "Dögun",
      "percent": 1.4
    },
    {
      "year": 2017,
      "constituency": "Norðvesturkjördæmi",
      "party": "Sjálfstæðisflokkur",
      "percent": 24.5
    },
    {
      "year": 2017,
      "constituency": "Norðvesturkjördæmi",
      "party": "Framsóknarflokkur",
      "percent": 18.4
    },
    {
      "year": 2017,
      "constituency": "Norðvesturkjördæmi",
      "party": "Vinstrihreyfingin - grænt framboð",
      "percent": 17.8
    },
    {
      "year": 2017,
      "constituency": "Norðvesturkjördæmi",
      "party": "Miðflokkurinn",
      "percent": 14.2
    },
    {
      "year": 2017,
      "constituency": "Norðvesturkjördæmi",
      "party": "Samfylkingin",
      "percent": 9.7
    },
    {
      "year": 2017,
      "constituency": "Norðvesturkjördæmi",
      "party": "Píratar",
      "percent": 6.8
    },
    {
      "year": 2017,
      "constituency": "Norðvesturkjördæmi",
      "party": "Flokkur fólksins",
      "percent": 5.3
    },
    {
      "year": 2017,
      "constituency": "Norðvesturkjördæmi",
      "party": "Viðreisn",
      "percent": 2.5
    },
    {
      "year": 2017,
      "constituency": "Norðvesturkjördæmi",
      "party": "Björt framtíð",
      "percent": 0.8
    },
    {
      "year": 2017,
      "constituency": "Norðausturkjördæmi",
      "party": "Sjálfstæðisflokkur",
      "percent": 20.3
    },
    {
      "year": 2017,
      "constituency": "Norðausturkjördæmi",
      "party": "Vinstrihreyfingin - grænt framboð",
      "percent": 19.9
    },
    {
      "year": 2017,
      "constituency": "Norðausturkjördæmi",
      "party": "Miðflokkurinn",
      "percent": 18.6
    },
    {
      "year": 2017,
      "constituency": "Norðausturkjördæmi",
      "party": "Framsóknarflokkur",
      "percent": 14.3
    },
    {
      "year": 2017,
      "constituency": "Norðausturkjördæmi",
      "party": "Samfylkingin",
      "percent": 13.9
    },
    {
      "year": 2017,
      "constituency": "Norðausturkjördæmi",
      "party": "Píratar",
      "percent": 5.5
    },
    {
      "year": 2017,
      "constituency": "Norðausturkjördæmi",
      "party": "Flokkur fólksins",
      "percent": 4.3
    },
    {
      "year": 2017,
      "constituency": "Norðausturkjördæmi",
      "party": "Viðreisn",
      "percent": 2.1
    },
    {
      "year": 2017,
      "constituency": "Norðausturkjördæmi",
      "party": "Björt framtíð",
      "percent": 0.7
    },
    {
      "year": 2017,
      "constituency": "Suðurkjördæmi",
      "party": "Sjálfstæðisflokkur",
      "percent": 25.2
    },
    {
      "year": 2017,
      "constituency": "Suðurkjördæmi",
      "party": "Framsóknarflokkur",
      "percent": 18.6
    },
    {
      "year": 2017,
      "constituency": "Suðurkjördæmi",
      "party": "Miðflokkurinn",
      "percent": 14.3
    },
    {
      "year": 2017,
      "constituency": "Suðurkjördæmi",
      "party": "Vinstrihreyfingin - grænt framboð",
      "percent": 11.8
    },
    {
      "year": 2017,
      "constituency": "Suðurkjördæmi",
      "party": "Samfylkingin",
      "percent": 9.6
    },
    {
      "year": 2017,
      "constituency": "Suðurkjördæmi",
      "party": "Flokkur fólksins",
      "percent": 8.9
    },
    {
      "year": 2017,
      "constituency": "Suðurkjördæmi",
      "party": "Píratar",
      "percent": 7.1
    },
    {
      "year": 2017,
      "constituency": "Suðurkjördæmi",
      "party": "Viðreisn",
      "percent": 3.1
    },
    {
      "year": 2017,
      "constituency": "Suðurkjördæmi",
      "party": "Björt framtíð",
      "percent": 1
    },
    {
      "year": 2017,
      "constituency": "Suðvesturkjördæmi",
      "party": "Sjálfstæðisflokkur",
      "percent": 30.9
    },
    {
      "year": 2017,
      "constituency": "Suðvesturkjördæmi",
      "party": "Vinstrihreyfingin - grænt framboð",
      "percent": 13.6
    },
    {
      "year": 2017,
      "constituency": "Suðvesturkjördæmi",
      "party": "Samfylkingin",
      "percent": 12.1
    },
    {
      "year": 2017,
      "constituency": "Suðvesturkjördæmi",
      "party": "Viðreisn",
      "percent": 9.5
    },
    {
      "year": 2017,
      "constituency": "Suðvesturkjördæmi",
      "party": "Miðflokkurinn",
      "percent": 9.5
    },
    {
      "year": 2017,
      "constituency": "Suðvesturkjördæmi",
      "party": "Píratar",
      "percent": 8.3
    },
    {
      "year": 2017,
      "constituency": "Suðvesturkjördæmi",
      "party": "Framsóknarflokkur",
      "percent": 7.9
    },
    {
      "year": 2017,
      "constituency": "Suðvesturkjördæmi",
      "party": "Flokkur fólksins",
      "percent": 6.5
    },
    {
      "year": 2017,
      "constituency": "Suðvesturkjördæmi",
      "party": "Björt framtíð",
      "percent": 1.5
    },
    {
      "year": 2017,
      "constituency": "Reykjavíkurkjördæmi suður",
      "party": "Sjálfstæðisflokkur",
      "percent": 22.8
    },
    {
      "year": 2017,
      "constituency": "Reykjavíkurkjördæmi suður",
      "party": "Vinstrihreyfingin - grænt framboð",
      "percent": 18.9
    },
    {
      "year": 2017,
      "constituency": "Reykjavíkurkjördæmi suður",
      "party": "Samfylkingin",
      "percent": 13
    },
    {
      "year": 2017,
      "constituency": "Reykjavíkurkjördæmi suður",
      "party": "Píratar",
      "percent": 11.4
    },
    {
      "year": 2017,
      "constituency": "Reykjavíkurkjördæmi suður",
      "party": "Viðreisn",
      "percent": 8.5
    },
    {
      "year": 2017,
      "constituency": "Reykjavíkurkjördæmi suður",
      "party": "Flokkur fólksins",
      "percent": 8.2
    },
    {
      "year": 2017,
      "constituency": "Reykjavíkurkjördæmi suður",
      "party": "Framsóknarflokkur",
      "percent": 8.1
    },
    {
      "year": 2017,
      "constituency": "Reykjavíkurkjördæmi suður",
      "party": "Miðflokkurinn",
      "percent": 7.6
    },
    {
      "year": 2017,
      "constituency": "Reykjavíkurkjördæmi suður",
      "party": "Björt framtíð",
      "percent": 1.3
    },
    {
      "year": 2017,
      "constituency": "Reykjavíkurkjördæmi norður",
      "party": "Sjálfstæðisflokkur",
      "percent": 22.6
    },
    {
      "year": 2017,
      "constituency": "Reykjavíkurkjördæmi norður",
      "party": "Vinstrihreyfingin - grænt framboð",
      "percent": 21.5
    },
    {
      "year": 2017,
      "constituency": "Reykjavíkurkjördæmi norður",
      "party": "Píratar",
      "percent": 13.6
    },
    {
      "year": 2017,
      "constituency": "Reykjavíkurkjördæmi norður",
      "party": "Samfylkingin",
      "percent": 12.8
    },
    {
      "year": 2017,
      "constituency": "Reykjavíkurkjördæmi norður",
      "party": "Viðreisn",
      "percent": 8.4
    },
    {
      "year": 2017,
      "constituency": "Reykjavíkurkjördæmi norður",
      "party": "Flokkur fólksins",
      "percent": 7.1
    },
    {
      "year": 2017,
      "constituency": "Reykjavíkurkjördæmi norður",
      "party": "Miðflokkurinn",
      "percent": 7
    },
    {
      "year": 2017,
      "constituency": "Reykjavíkurkjördæmi norður",
      "party": "Framsóknarflokkur",
      "percent": 5.3
    },
    {
      "year": 2017,
      "constituency": "Reykjavíkurkjördæmi norður",
      "party": "Björt framtíð",
      "percent": 1.4
    },
    {
      "year": 2021,
      "constituency": "Norðvesturkjördæmi",
      "party": "Framsóknarflokkur",
      "percent": 25.8
    },
    {
      "year": 2021,
      "constituency": "Norðvesturkjördæmi",
      "party": "Sjálfstæðisflokkur",
      "percent": 22.6
    },
    {
      "year": 2021,
      "constituency": "Norðvesturkjördæmi",
      "party": "Vinstrihreyfingin - grænt framboð",
      "percent": 11.5
    },
    {
      "year": 2021,
      "constituency": "Norðvesturkjördæmi",
      "party": "Flokkur fólksins",
      "percent": 8.8
    },
    {
      "year": 2021,
      "constituency": "Norðvesturkjördæmi",
      "party": "Miðflokkurinn",
      "percent": 7.4
    },
    {
      "year": 2021,
      "constituency": "Norðvesturkjördæmi",
      "party": "Samfylkingin",
      "percent": 6.9
    },
    {
      "year": 2021,
      "constituency": "Norðvesturkjördæmi",
      "party": "Píratar",
      "percent": 6.3
    },
    {
      "year": 2021,
      "constituency": "Norðvesturkjördæmi",
      "party": "Viðreisn",
      "percent": 6.2
    },
    {
      "year": 2021,
      "constituency": "Norðvesturkjördæmi",
      "party": "Sósíalistaflokkur Íslands",
      "percent": 4.2
    },
    {
      "year": 2021,
      "constituency": "Norðausturkjördæmi",
      "party": "Framsóknarflokkur",
      "percent": 25.6
    },
    {
      "year": 2021,
      "constituency": "Norðausturkjördæmi",
      "party": "Sjálfstæðisflokkur",
      "percent": 18.5
    },
    {
      "year": 2021,
      "constituency": "Norðausturkjördæmi",
      "party": "Vinstrihreyfingin - grænt framboð",
      "percent": 12.9
    },
    {
      "year": 2021,
      "constituency": "Norðausturkjördæmi",
      "party": "Samfylkingin",
      "percent": 10.5
    },
    {
      "year": 2021,
      "constituency": "Norðausturkjördæmi",
      "party": "Miðflokkurinn",
      "percent": 8.9
    },
    {
      "year": 2021,
      "constituency": "Norðausturkjördæmi",
      "party": "Flokkur fólksins",
      "percent": 8.6
    },
    {
      "year": 2021,
      "constituency": "Norðausturkjördæmi",
      "party": "Viðreisn",
      "percent": 5.4
    },
    {
      "year": 2021,
      "constituency": "Norðausturkjördæmi",
      "party": "Píratar",
      "percent": 5.3
    },
    {
      "year": 2021,
      "constituency": "Norðausturkjördæmi",
      "party": "Sósíalistaflokkur Íslands",
      "percent": 4.1
    },
    {
      "year": 2021,
      "constituency": "Suðurkjördæmi",
      "party": "Sjálfstæðisflokkur",
      "percent": 24.6
    },
    {
      "year": 2021,
      "constituency": "Suðurkjördæmi",
      "party": "Framsóknarflokkur",
      "percent": 23.9
    },
    {
      "year": 2021,
      "constituency": "Suðurkjördæmi",
      "party": "Flokkur fólksins",
      "percent": 12.9
    },
    {
      "year": 2021,
      "constituency": "Suðurkjördæmi",
      "party": "Samfylkingin",
      "percent": 7.6
    },
    {
      "year": 2021,
      "constituency": "Suðurkjördæmi",
      "party": "Miðflokkurinn",
      "percent": 7.4
    },
    {
      "year": 2021,
      "constituency": "Suðurkjördæmi",
      "party": "Vinstrihreyfingin - grænt framboð",
      "percent": 7.4
    },
    {
      "year": 2021,
      "constituency": "Suðurkjördæmi",
      "party": "Viðreisn",
      "percent": 6.2
    },
    {
      "year": 2021,
      "constituency": "Suðurkjördæmi",
      "party": "Píratar",
      "percent": 5.6
    },
    {
      "year": 2021,
      "constituency": "Suðurkjördæmi",
      "party": "Sósíalistaflokkur Íslands",
      "percent": 3.7
    },
    {
      "year": 2021,
      "constituency": "Suðvesturkjördæmi",
      "party": "Sjálfstæðisflokkur",
      "percent": 30.3
    },
    {
      "year": 2021,
      "constituency": "Suðvesturkjördæmi",
      "party": "Framsóknarflokkur",
      "percent": 14.5
    },
    {
      "year": 2021,
      "constituency": "Suðvesturkjördæmi",
      "party": "Vinstrihreyfingin - grænt framboð",
      "percent": 12.1
    },
    {
      "year": 2021,
      "constituency": "Suðvesturkjördæmi",
      "party": "Viðreisn",
      "percent": 11.4
    },
    {
      "year": 2021,
      "constituency": "Suðvesturkjördæmi",
      "party": "Píratar",
      "percent": 8.3
    },
    {
      "year": 2021,
      "constituency": "Suðvesturkjördæmi",
      "party": "Samfylkingin",
      "percent": 8.1
    },
    {
      "year": 2021,
      "constituency": "Suðvesturkjördæmi",
      "party": "Flokkur fólksins",
      "percent": 7.6
    },
    {
      "year": 2021,
      "constituency": "Suðvesturkjördæmi",
      "party": "Miðflokkurinn",
      "percent": 4.5
    },
    {
      "year": 2021,
      "constituency": "Suðvesturkjördæmi",
      "party": "Sósíalistaflokkur Íslands",
      "percent": 3
    },
    {
      "year": 2021,
      "constituency": "Reykjavíkurkjördæmi suður",
      "party": "Sjálfstæðisflokkur",
      "percent": 22.8
    },
    {
      "year": 2021,
      "constituency": "Reykjavíkurkjördæmi suður",
      "party": "Vinstrihreyfingin - grænt framboð",
      "percent": 14.7
    },
    {
      "year": 2021,
      "constituency": "Reykjavíkurkjördæmi suður",
      "party": "Samfylkingin",
      "percent": 13.3
    },
    {
      "year": 2021,
      "constituency": "Reykjavíkurkjördæmi suður",
      "party": "Framsóknarflokkur",
      "percent": 11.5
    },
    {
      "year": 2021,
      "constituency": "Reykjavíkurkjördæmi suður",
      "party": "Píratar",
      "percent": 10.9
    },
    {
      "year": 2021,
      "constituency": "Reykjavíkurkjördæmi suður",
      "party": "Flokkur fólksins",
      "percent": 8.9
    },
    {
      "year": 2021,
      "constituency": "Reykjavíkurkjördæmi suður",
      "party": "Viðreisn",
      "percent": 8.6
    },
    {
      "year": 2021,
      "constituency": "Reykjavíkurkjördæmi suður",
      "party": "Sósíalistaflokkur Íslands",
      "percent": 4.8
    },
    {
      "year": 2021,
      "constituency": "Reykjavíkurkjördæmi suður",
      "party": "Miðflokkurinn",
      "percent": 4.1
    },
    {
      "year": 2021,
      "constituency": "Reykjavíkurkjördæmi norður",
      "party": "Sjálfstæðisflokkur",
      "percent": 20.9
    },
    {
      "year": 2021,
      "constituency": "Reykjavíkurkjördæmi norður",
      "party": "Vinstrihreyfingin - grænt framboð",
      "percent": 15.9
    },
    {
      "year": 2021,
      "constituency": "Reykjavíkurkjördæmi norður",
      "party": "Píratar",
      "percent": 12.8
    },
    {
      "year": 2021,
      "constituency": "Reykjavíkurkjördæmi norður",
      "party": "Samfylkingin",
      "percent": 12.6
    },
    {
      "year": 2021,
      "constituency": "Reykjavíkurkjördæmi norður",
      "party": "Framsóknarflokkur",
      "percent": 12.3
    },
    {
      "year": 2021,
      "constituency": "Reykjavíkurkjördæmi norður",
      "party": "Viðreisn",
      "percent": 7.7
    },
    {
      "year": 2021,
      "constituency": "Reykjavíkurkjördæmi norður",
      "party": "Flokkur fólksins",
      "percent": 7.7
    },
    {
      "year": 2021,
      "constituency": "Reykjavíkurkjördæmi norður",
      "party": "Sósíalistaflokkur Íslands",
      "percent": 5.6
    },
    {
      "year": 2021,
      "constituency": "Reykjavíkurkjördæmi norður",
      "party": "Miðflokkurinn",
      "percent": 3.5
    },
    {
      "year": 2024,
      "constituency": "Norðvesturkjördæmi",
      "party": "Sjálfstæðisflokkur",
      "percent": 18
    },
    {
      "year": 2024,
      "constituency": "Norðvesturkjördæmi",
      "party": "Flokkur fólksins",
      "percent": 16.7
    },
    {
      "year": 2024,
      "constituency": "Norðvesturkjördæmi",
      "party": "Samfylkingin",
      "percent": 15.9
    },
    {
      "year": 2024,
      "constituency": "Norðvesturkjördæmi",
      "party": "Miðflokkurinn",
      "percent": 14.8
    },
    {
      "year": 2024,
      "constituency": "Norðvesturkjördæmi",
      "party": "Framsóknarflokkur",
      "percent": 13.3
    },
    {
      "year": 2024,
      "constituency": "Norðvesturkjördæmi",
      "party": "Viðreisn",
      "percent": 12.6
    },
    {
      "year": 2024,
      "constituency": "Norðvesturkjördæmi",
      "party": "Sósíalistaflokkur Íslands",
      "percent": 3.4
    },
    {
      "year": 2024,
      "constituency": "Norðvesturkjördæmi",
      "party": "Vinstrihreyfingin - grænt framboð",
      "percent": 2.7
    },
    {
      "year": 2024,
      "constituency": "Norðvesturkjördæmi",
      "party": "Píratar",
      "percent": 1.8
    },
    {
      "year": 2024,
      "constituency": "Norðausturkjördæmi",
      "party": "Samfylkingin",
      "percent": 21.3
    },
    {
      "year": 2024,
      "constituency": "Norðausturkjördæmi",
      "party": "Miðflokkurinn",
      "percent": 15.7
    },
    {
      "year": 2024,
      "constituency": "Norðausturkjördæmi",
      "party": "Sjálfstæðisflokkur",
      "percent": 15
    },
    {
      "year": 2024,
      "constituency": "Norðausturkjördæmi",
      "party": "Flokkur fólksins",
      "percent": 14.3
    },
    {
      "year": 2024,
      "constituency": "Norðausturkjördæmi",
      "party": "Framsóknarflokkur",
      "percent": 14.2
    },
    {
      "year": 2024,
      "constituency": "Norðausturkjördæmi",
      "party": "Viðreisn",
      "percent": 9.4
    },
    {
      "year": 2024,
      "constituency": "Norðausturkjördæmi",
      "party": "Sósíalistaflokkur Íslands",
      "percent": 3.8
    },
    {
      "year": 2024,
      "constituency": "Norðausturkjördæmi",
      "party": "Vinstrihreyfingin - grænt framboð",
      "percent": 3.8
    },
    {
      "year": 2024,
      "constituency": "Norðausturkjördæmi",
      "party": "Píratar",
      "percent": 1.8
    },
    {
      "year": 2024,
      "constituency": "Suðurkjördæmi",
      "party": "Flokkur fólksins",
      "percent": 20
    },
    {
      "year": 2024,
      "constituency": "Suðurkjördæmi",
      "party": "Sjálfstæðisflokkur",
      "percent": 19.6
    },
    {
      "year": 2024,
      "constituency": "Suðurkjördæmi",
      "party": "Samfylkingin",
      "percent": 17.3
    },
    {
      "year": 2024,
      "constituency": "Suðurkjördæmi",
      "party": "Miðflokkurinn",
      "percent": 13.6
    },
    {
      "year": 2024,
      "constituency": "Suðurkjördæmi",
      "party": "Framsóknarflokkur",
      "percent": 12
    },
    {
      "year": 2024,
      "constituency": "Suðurkjördæmi",
      "party": "Viðreisn",
      "percent": 11.2
    },
    {
      "year": 2024,
      "constituency": "Suðurkjördæmi",
      "party": "Sósíalistaflokkur Íslands",
      "percent": 2.4
    },
    {
      "year": 2024,
      "constituency": "Suðurkjördæmi",
      "party": "Lýðræðisflokkur",
      "percent": 1.3
    },
    {
      "year": 2024,
      "constituency": "Suðurkjördæmi",
      "party": "Píratar",
      "percent": 1.3
    },
    {
      "year": 2024,
      "constituency": "Suðvesturkjördæmi",
      "party": "Sjálfstæðisflokkur",
      "percent": 23.4
    },
    {
      "year": 2024,
      "constituency": "Suðvesturkjördæmi",
      "party": "Viðreisn",
      "percent": 20.1
    },
    {
      "year": 2024,
      "constituency": "Suðvesturkjördæmi",
      "party": "Samfylkingin",
      "percent": 19.3
    },
    {
      "year": 2024,
      "constituency": "Suðvesturkjördæmi",
      "party": "Miðflokkurinn",
      "percent": 12
    },
    {
      "year": 2024,
      "constituency": "Suðvesturkjördæmi",
      "party": "Flokkur fólksins",
      "percent": 11
    },
    {
      "year": 2024,
      "constituency": "Suðvesturkjördæmi",
      "party": "Framsóknarflokkur",
      "percent": 5.9
    },
    {
      "year": 2024,
      "constituency": "Suðvesturkjördæmi",
      "party": "Sósíalistaflokkur Íslands",
      "percent": 2.8
    },
    {
      "year": 2024,
      "constituency": "Suðvesturkjördæmi",
      "party": "Píratar",
      "percent": 2.8
    },
    {
      "year": 2024,
      "constituency": "Suðvesturkjördæmi",
      "party": "Vinstrihreyfingin - grænt framboð",
      "percent": 1.5
    },
    {
      "year": 2024,
      "constituency": "Reykjavíkurkjördæmi suður",
      "party": "Samfylkingin",
      "percent": 22.9
    },
    {
      "year": 2024,
      "constituency": "Reykjavíkurkjördæmi suður",
      "party": "Viðreisn",
      "percent": 17.7
    },
    {
      "year": 2024,
      "constituency": "Reykjavíkurkjördæmi suður",
      "party": "Sjálfstæðisflokkur",
      "percent": 17.6
    },
    {
      "year": 2024,
      "constituency": "Reykjavíkurkjördæmi suður",
      "party": "Flokkur fólksins",
      "percent": 13.5
    },
    {
      "year": 2024,
      "constituency": "Reykjavíkurkjördæmi suður",
      "party": "Miðflokkurinn",
      "percent": 10.5
    },
    {
      "year": 2024,
      "constituency": "Reykjavíkurkjördæmi suður",
      "party": "Sósíalistaflokkur Íslands",
      "percent": 5.6
    },
    {
      "year": 2024,
      "constituency": "Reykjavíkurkjördæmi suður",
      "party": "Framsóknarflokkur",
      "percent": 4.4
    },
    {
      "year": 2024,
      "constituency": "Reykjavíkurkjördæmi suður",
      "party": "Píratar",
      "percent": 3.9
    },
    {
      "year": 2024,
      "constituency": "Reykjavíkurkjördæmi suður",
      "party": "Vinstrihreyfingin - grænt framboð",
      "percent": 2.9
    },
    {
      "year": 2024,
      "constituency": "Reykjavíkurkjördæmi norður",
      "party": "Samfylkingin",
      "percent": 26.1
    },
    {
      "year": 2024,
      "constituency": "Reykjavíkurkjördæmi norður",
      "party": "Sjálfstæðisflokkur",
      "percent": 17.4
    },
    {
      "year": 2024,
      "constituency": "Reykjavíkurkjördæmi norður",
      "party": "Viðreisn",
      "percent": 16.3
    },
    {
      "year": 2024,
      "constituency": "Reykjavíkurkjördæmi norður",
      "party": "Flokkur fólksins",
      "percent": 11.9
    },
    {
      "year": 2024,
      "constituency": "Reykjavíkurkjördæmi norður",
      "party": "Miðflokkurinn",
      "percent": 8.9
    },
    {
      "year": 2024,
      "constituency": "Reykjavíkurkjördæmi norður",
      "party": "Sósíalistaflokkur Íslands",
      "percent": 5.9
    },
    {
      "year": 2024,
      "constituency": "Reykjavíkurkjördæmi norður",
      "party": "Píratar",
      "percent": 5.4
    },
    {
      "year": 2024,
      "constituency": "Reykjavíkurkjördæmi norður",
      "party": "Framsóknarflokkur",
      "percent": 4
    },
    {
      "year": 2024,
      "constituency": "Reykjavíkurkjördæmi norður",
      "party": "Vinstrihreyfingin - grænt framboð",
      "percent": 2.9
    }
  ]
}